README.rst
_description.org
lh-agpl3-LICENSE.txt
pyproject.toml
setup.py
bin/bashIcmSelfcontainedExample.sh
bin/bashIcmStandaloneExample.sh
bin/exmpl-conv-sameInstance.py
bin/exmpl-mu-many.cs
bisos/__init__.py
bisos.examples.egg-info/PKG-INFO
bisos.examples.egg-info/SOURCES.txt
bisos.examples.egg-info/dependency_links.txt
bisos.examples.egg-info/not-zip-safe
bisos.examples.egg-info/requires.txt
bisos.examples.egg-info/top_level.txt
bisos/examples/__init__.py
bisos/examples/fp_csu.py
bisos/examples/io_csu.py
bisos/examples/parsArgsStdinCmndResult_csu.py
bisos/examples/pattern_csu.py
bisos/examples/platformConfigs_csu.py
bisos/examples/pyRunAs_csu.py
bisos/examples/subProcOps_csu.py